orama/__init__.py
orama/cloud.py
orama/collection.py
orama/common.py
orama/constants.py
orama/manager.py
orama/profile.py
orama/stream_manager.py
orama/types.py
orama/utils.py
oramacore_client-1.2.0.dist-info/licenses/LICENSE
oramacore_client-1.2.0.dist-info/METADATA
oramacore_client-1.2.0.dist-info/WHEEL
oramacore_client-1.2.0.dist-info/top_level.txt
oramacore_client-1.2.0.dist-info/RECORD
