Metadata-Version: 2.4
Name: oramacore-client
Version: 1.2.0
Summary: Python client for OramaCore and Orama Cloud
Home-page: https://github.com/oramasearch/oramacore-client-python
Author: Orama
Author-email: Orama Team <info@orama.com>
License: # GNU AFFERO GENERAL PUBLIC LICENSE
Project-URL: Homepage, https://github.com/oramasearch/oramacore-client-python
Project-URL: Documentation, https://docs.orama.com
Project-URL: Repository, https://github.com/oramasearch/oramacore-client-python.git
Project-URL: Bug Reports, https://github.com/oramasearch/oramacore-client-python/issues
Keywords: search,vector database,embeddings,AI,LLM,full-text search
Classifier: Development Status :: 4 - Beta
Classifier: Intended Audience :: Developers
Classifier: License :: OSI Approved :: GNU Affero General Public License v3
Classifier: Operating System :: OS Independent
Classifier: Programming Language :: Python :: 3
Classifier: Programming Language :: Python :: 3.8
Classifier: Programming Language :: Python :: 3.9
Classifier: Programming Language :: Python :: 3.10
Classifier: Programming Language :: Python :: 3.11
Classifier: Programming Language :: Python :: 3.12
Classifier: Topic :: Internet :: WWW/HTTP :: Indexing/Search
Classifier: Topic :: Software Development :: Libraries :: Python Modules
Requires-Python: >=3.8
License-File: LICENSE
Requires-Dist: aiohttp>=3.8.0
Requires-Dist: typing-extensions>=4.0.0
Provides-Extra: dev
Requires-Dist: pytest>=7.0.0; extra == "dev"
Requires-Dist: pytest-asyncio>=0.21.0; extra == "dev"
Requires-Dist: black>=22.0.0; extra == "dev"
Requires-Dist: flake8>=5.0.0; extra == "dev"
Requires-Dist: mypy>=1.0.0; extra == "dev"
Requires-Dist: isort>=5.0.0; extra == "dev"
Requires-Dist: pre-commit>=3.0.0; extra == "dev"
Dynamic: author
Dynamic: home-page
Dynamic: license-file
Dynamic: requires-python
